[
	{
		"city": "Chalons  - Ambulance n°224",
		"departement": "Marne",
		"country": "France"
	},
	{
		"city": "Châlons - Annexe Saint Maur de l'Hôtel Dieu",
		"departement": "Marne",
		"country": "France"
	},
	{
		"city": "Châlons - Hôpital Temporaire n°1",
		"departement": "Marne",
		"country": "France"
	},
	{
		"city": "Châlons en Champagne",
		"departement": "Marne",
		"country": "France"
	},
	{
		"city": "Chalons en Champagne - Hôpital",
		"departement": "Marne",
		"country": "France"
	},
	{
		"city": "Châlons en Champagne - Hôpital Temporaire n°17",
		"departement": "Marne",
		"country": "France"
	},
	{
		"city": "Chalons sir Marne - Hôpital n°20",
		"departement": "Marne",
		"country": "France"
	},
	{
		"city": "Chalons sur Marne",
		"departement": "Marne",
		"country": "France"
	},
	{
		"city": "Châlons sur Marne - Ambulance",
		"departement": "Marne",
		"country": "France"
	},
	{
		"city": "Châlons sur Marne - Ambulance 1/6",
		"departement": "Marne",
		"country": "France"
	},
	{
		"city": "Châlons sur Marne - Ambulance 13/20",
		"departement": "Marne",
		"country": "France"
	},
	{
		"city": "Châlons sur Marne - Ambulance n°4",
		"departement": "Marne",
		"country": "France"
	},
	{
		"city": "Châlons sur Marne - Ambulance Saint Maur",
		"departement": "Marne",
		"country": "France"
	},
	{
		"city": "Châlons sur Marne - Camp de Châlons",
		"departement": "Marne",
		"country": "France"
	},
	{
		"city": "Chalons sur Marne - Hôpital",
		"departement": "Marne",
		"country": "France"
	},
	{
		"city": "Châlons sur Marne - Hôpital",
		"departement": "Marne",
		"country": "France"
	},
	{
		"city": "Chalons sur Marne - Hôpital Civil",
		"departement": "Marne",
		"country": "France"
	},
	{
		"city": "Châlons sur Marne - Hôpital Civil",
		"departement": "Marne",
		"country": "France"
	},
	{
		"city": "Châlons sur Marne - Hôpital Complémentaire A",
		"departement": "Marne",
		"country": "France"
	},
	{
		"city": "Chalons sur Marne - Hôpital Complémentaire Corbineau",
		"departement": "Marne",
		"country": "France"
	},
	{
		"city": "Chalons sur Marne - Hôpital Complémentaire n°18 Corbineau",
		"departement": "Marne",
		"country": "France"
	},
	{
		"city": "Chalons sur Marne - Hôpital Complémentaire n°4",
		"departement": "Marne",
		"country": "France"
	},
	{
		"city": "Châlons sur Marne - Hôpital Corbineau",
		"departement": "Marne",
		"country": "France"
	},
	{
		"city": "Châlons sur Marne - Hôpital Février",
		"departement": "Marne",
		"country": "France"
	},
	{
		"city": "Châlons sur Marne - Hôpital Militaire Complémentaire",
		"departement": "Marne",
		"country": "France"
	},
	{
		"city": "Chalons sur Marne - Hôpital Militaire du Camp",
		"departement": "Marne",
		"country": "France"
	},
	{
		"city": "Châlons sur Marne - Hôpital n°19",
		"departement": "Marne",
		"country": "France"
	},
	{
		"city": "Châlons sur Marne - Hôpital n°38",
		"departement": "Marne",
		"country": "France"
	},
	{
		"city": "Chalons sur Marne - Hôpital Saint Maur",
		"departement": "Marne",
		"country": "France"
	},
	{
		"city": "Chalons sur Marne - Hôpital Sainte Croix",
		"departement": "Marne",
		"country": "France"
	},
	{
		"city": "Châlons sur Marne - Hôpital Temporaire n°15",
		"departement": "Marne",
		"country": "France"
	},
	{
		"city": "Chalons sur Marne - Hôpital Temporaire n°17",
		"departement": "Marne",
		"country": "France"
	},
	{
		"city": "Châlons sur Marne - Hôpital Temporaire n°17",
		"departement": "Marne",
		"country": "France"
	},
	{
		"city": "Châlons sur Marne - Hôpital Temporaire n°18",
		"departement": "Marne",
		"country": "France"
	},
	{
		"city": "Châlons sur Marne - Hôpital Temporaire n°2",
		"departement": "Marne",
		"country": "France"
	},
	{
		"city": "Châlons sur Marne - Hôpital Temporaire n°8",
		"departement": "Marne",
		"country": "France"
	},
	{
		"city": "Chalons sur Vesle - Ambulance 4/1",
		"departement": "Marne",
		"country": "France"
	},
	{
		"city": "Chalons-sur-Marne",
		"departement": "Marne",
		"country": "France"
	},
	{
		"city": "Châlons-sur-Marne",
		"departement": "Marne",
		"country": "France"
	},
	{
		"city": "Châlons-sur-Marne - Ambulance Saint-Maur",
		"departement": "Marne",
		"country": "France"
	},
	{
		"city": "Chalons-sur-Marne - Annexe de l'hôpital",
		"departement": "Marne",
		"country": "France"
	},
	{
		"city": "Châlons-sur-Marne - Hôpital complémentaire n° 37",
		"departement": "Marne",
		"country": "France"
	},
	{
		"city": "Châlons-sur-Marne - Hôpital Complémentaire n°19",
		"departement": "Marne",
		"country": "France"
	},
	{
		"city": "Châlons-sur-Marne - Hôpital Corbineau",
		"departement": "Marne",
		"country": "France"
	},
	{
		"city": "Chalons-sur-Marne - Hôpital Corps d'Armée n°54",
		"departement": "Marne",
		"country": "France"
	},
	{
		"city": "Chalons-sur-Marne - Hopital Sainte Croix",
		"departement": "Marne",
		"country": "France"
	},
	{
		"city": "Châlons-sur-Marne - Hôpital Sainte-Croix",
		"departement": "Marne",
		"country": "France"
	},
	{
		"city": "Chalons-sur-Marne - Hôpital Temporaire",
		"departement": "Marne",
		"country": "France"
	},
	{
		"city": "Châlons-sur-Marne - Hôpital Temporaire",
		"departement": "Marne",
		"country": "France"
	},
	{
		"city": "Chalons-sur-Marne - Hôpital Temporaire n°1",
		"departement": "Marne",
		"country": "France"
	},
	{
		"city": "Châlons-sur-Marne - Hôpital Temporaire n°17",
		"departement": "Marne",
		"country": "France"
	},
	{
		"city": "Châlons-sur-Marne (hôpital militaire)",
		"departement": "Marne",
		"country": "France"
	},
	{
		"city": "Chambéry",
		"departement": "Savoie",
		"country": "France"
	},
	{
		"city": "Chambery - Hôpital",
		"departement": "Savoie",
		"country": "France"
	},
	{
		"city": "Chambéry - Hopital militaire de Chambéry",
		"departement": "Savoie",
		"country": "France"
	},
	{
		"city": "Chambéry - Hôpital Régional",
		"departement": "Savoie",
		"country": "France"
	},
	{
		"city": "Chambry",
		"departement": "Seine-et-Marne",
		"country": "France"
	},
	{
		"city": "Champ de Bataille de Compiègne",
		"departement": "Oise",
		"country": "France"
	},
	{
		"city": "Champagne",
		"departement": "Marne",
		"country": "France"
	},
	{
		"city": "Champenaux",
		"departement": "Meurthe et Mozelle",
		"country": "France"
	},
	{
		"city": "Champenoux",
		"departement": "Meurthe-et-Moselle",
		"country": "France"
	},
	{
		"city": "Champigneulles",
		"departement": "Meurthe-et-Moselle",
		"country": "France"
	},
	{
		"city": "Champlon",
		"departement": "Meuse",
		"country": "France"
	},
	{
		"city": "champs de bataille",
		"departement": "Marne",
		"country": "France"
	},
	{
		"city": "Champteussé"
	},
	{
		"city": "Champtocé"
	},
	{
		"city": "Champtoceaux"
	},
	{
		"city": "Champvoisy",
		"departement": "Marne",
		"country": "France"
	},
	{
		"city": "Chanfontaine - HOE 21/1",
		"departement": "Meurthe-et-Moselle",
		"country": "France"
	},
	{
		"city": "Chantecler",
		"departement": "Pas-de-Calais",
		"country": "France"
	},
	{
		"city": "Chantenay"
	},
	{
		"city": "Chantenay-sur-Loire"
	},
	{
		"city": "Chapelle-Basse-Mer",
		"departement": "Loire Inférieure",
		"country": "France"
	},
	{
		"city": "Chapelle-Saint-Pantaleon - Sous Secteur Plat Chêne",
		"departement": "Meuse",
		"country": "France"
	},
	{
		"city": "Charleville - Ambulance",
		"departement": "Ardennes",
		"country": "France"
	},
	{
		"city": "Charleville - Ambulance 3/64",
		"departement": "Ardennes",
		"country": "France"
	},
	{
		"city": "Charleville - Hôpital",
		"departement": "Ardennes",
		"country": "France"
	},
	{
		"city": "Charlognes",
		"departement": "Ardennes",
		"country": "France"
	},
	{
		"city": "Charly-sur-Marne - Ambulance 10/21",
		"departement": "Aisne",
		"country": "France"
	},
	{
		"city": "Charmes - Hôpital Mixte",
		"departement": "Vosges",
		"country": "France"
	},
	{
		"city": "Charmont",
		"departement": "Aube",
		"country": "France"
	},
	{
		"city": "Charonne",
		"departement": "Aisne",
		"country": "France"
	},
	{
		"city": "Chartèves",
		"departement": "Aisne",
		"country": "France"
	},
	{
		"city": "Chartres",
		"departement": "Eure-et-Loir",
		"country": "France"
	},
	{
		"city": "Chartres - Gare",
		"departement": "Eure-et-Loir",
		"country": "France"
	},
	{
		"city": "Chartres - Hôpital Mixte",
		"departement": "Eure-et-Loir",
		"country": "France"
	},
	{
		"city": "Chartres - Hôpital Temporaire n°36",
		"departement": "Eure-et-Loir",
		"country": "France"
	},
	{
		"city": "Chartres - La Gare",
		"departement": "Eure-et-Loir",
		"country": "France"
	},
	{
		"city": "Chasseny",
		"departement": "Aisne",
		"country": "France"
	},
	{
		"city": "Chasseny - Ambulance 13/8",
		"departement": "Aisne",
		"country": "France"
	},
	{
		"city": "Château Chinon - Hôpital Temporaire n°66",
		"departement": "Nièvre",
		"country": "France"
	},
	{
		"city": "Château de Boursault - Ambulance 10/6",
		"departement": "Marne",
		"country": "France"
	},
	{
		"city": "Château de la Trapperie - Ambulance 5/11",
		"departement": "Belgique",
		"country": "Belgique"
	},
	{
		"city": "Château de la Trapperie - Habbaye-la-Vieille - Ambulance n°5/11",
		"departement": "Belgique",
		"country": "Belgique"
	},
	{
		"city": "Château de Limé",
		"departement": "Aisne",
		"country": "France"
	},
	{
		"city": "Château de Montgivroux",
		"departement": "Marne",
		"country": "France"
	},
	{
		"city": "Château de Sorel",
		"departement": "Oise",
		"country": "France"
	},
	{
		"city": "Château Gonthier",
		"departement": "Mayenne",
		"country": "France"
	},
	{
		"city": "Château Thierry",
		"departement": "Aisne",
		"country": "France"
	},
	{
		"city": "Château Thierry - Ambulance n°14/4",
		"departement": "Aisne",
		"country": "France"
	},
	{
		"city": "Château Thierry - Côte 204",
		"departement": "Aisne",
		"country": "France"
	},
	{
		"city": "Château Thierry - Côte 204 Ouest",
		"departement": "Aisne",
		"country": "France"
	},
	{
		"city": "Château-Chinon",
		"departement": "Nièvre",
		"country": "France"
	},
	{
		"city": "Château-de-Beth",
		"departement": "Belgique",
		"country": "Belgique"
	},
	{
		"city": "Château-du-Loir",
		"departement": "Sarthe",
		"country": "France"
	},
	{
		"city": "Château-sur-Loire"
	},
	{
		"city": "Château-Thébaud"
	},
	{
		"city": "Château-Thierry",
		"departement": "Aisne",
		"country": "France"
	},
	{
		"city": "Château-Thierry Cote 204",
		"departement": "Aisne",
		"country": "France"
	},
	{
		"city": "Chateaubriant",
		"departement": "Loire Inférieure",
		"country": "France"
	},
	{
		"city": "Châteaubriant"
	},
	{
		"city": "Châteaudun",
		"departement": "Eure-et-Loir",
		"country": "France"
	},
	{
		"city": "Chateauponsac"
	},
	{
		"city": "Châteauroux",
		"departement": "Indre",
		"country": "France"
	},
	{
		"city": "Châteauroux - Hôpital Auxiliaire",
		"departement": "Indre",
		"country": "France"
	},
	{
		"city": "Chateauroux - Hopital mixte",
		"departement": "Indre",
		"country": "France"
	},
	{
		"city": "Châtelguyon",
		"departement": "Puy-de-Dôme",
		"country": "France"
	},
	{
		"city": "Châtellerault"
	},
	{
		"city": "Châtelraould",
		"departement": "Marne",
		"country": "France"
	},
	{
		"city": "Chatillon sur Marne - Prieuré de Binson",
		"departement": "Marne",
		"country": "France"
	},
	{
		"city": "Châtillon-sur-Marne",
		"departement": "Marne",
		"country": "France"
	},
	{
		"city": "Chatillon-sur-Sévre"
	},
	{
		"city": "Chattancourt",
		"departement": "Meuse",
		"country": "France"
	},
	{
		"city": "Chattancourt - Combats de Verdun",
		"departement": "Meuse",
		"country": "France"
	},
	{
		"city": "Chattencourt - Combats de Verdun",
		"departement": "Meuse",
		"country": "France"
	},
	{
		"city": "Chaudefontaine",
		"departement": "Marne",
		"country": "France"
	},
	{
		"city": "Chaudefontaine - Ambulance 3/151",
		"departement": "Marne",
		"country": "France"
	},
	{
		"city": "Chaudun",
		"departement": "Aisne",
		"country": "France"
	},
	{
		"city": "Chaulnes",
		"departement": "Somme",
		"country": "France"
	},
	{
		"city": "Chaumon Saint Quentin",
		"departement": "Ardennes",
		"country": "France"
	},
	{
		"city": "Chaumont",
		"departement": "Haute-Marne",
		"country": "France"
	},
	{
		"city": "Chaumont en Vexin",
		"departement": "Oise",
		"country": "France"
	},
	{
		"city": "Chaumont saint Quentin",
		"departement": "Ardennes",
		"country": "France"
	},
	{
		"city": "Chaumont Saint Quentin",
		"departement": "Ardennes",
		"country": "France"
	},
	{
		"city": "Chaumont St Quentin",
		"departement": "Ardennes",
		"country": "France"
	},
	{
		"city": "Chaumont sur Aire",
		"departement": "Meuse",
		"country": "France"
	},
	{
		"city": "Chaumont sur Aire - Ambulance n°235",
		"departement": "Meuse",
		"country": "France"
	},
	{
		"city": "Chaumont-Saint-Quentin",
		"departement": "Ardennes",
		"country": "France"
	},
	{
		"city": "Chaumont-sur-Aire",
		"departement": "Meuse",
		"country": "France"
	},
	{
		"city": "Chauny",
		"departement": "Aisne",
		"country": "France"
	},
	{
		"city": "Chauny - Ambulance 204",
		"departement": "Aisne",
		"country": "France"
	},
	{
		"city": "Chauny - Ambulance n°2/73",
		"departement": "Aisne",
		"country": "France"
	},
	{
		"city": "Chauny - Hôpital Chirurgical",
		"departement": "Aisne",
		"country": "France"
	},
	{
		"city": "Chaussoy - Epagny",
		"departement": "Somme",
		"country": "France"
	},
	{
		"city": "Chauvé"
	},
	{
		"city": "Chavignon",
		"departement": "Aisne",
		"country": "France"
	},
	{
		"city": "Chavigny",
		"departement": "Aisne",
		"country": "France"
	},
	{
		"city": "Chazé-Henry"
	},
	{
		"city": "Cheix"
	},
	{
		"city": "Cheix en Retz",
		"departement": "Loire Inférieure",
		"country": "France"
	},
	{
		"city": "Cheix-en-Retz"
	},
	{
		"city": "Chéméré"
	},
	{
		"city": "Chemille",
		"departement": "Maine-et-Loire",
		"country": "France"
	},
	{
		"city": "Chemin des Dames",
		"departement": "Aisne",
		"country": "France"
	},
	{
		"city": "Chemnitz",
		"departement": "Allemagne",
		"country": "Allemagne"
	},
	{
		"city": "Chenonceau",
		"departement": "Indre-et-Loire",
		"country": "France"
	},
	{
		"city": "Cheppy",
		"departement": "Meuse",
		"country": "France"
	},
	{
		"city": "Chépy",
		"departement": "Marne",
		"country": "France"
	},
	{
		"city": "Cherbourg"
	},
	{
		"city": "Cherbourg - Hôpital",
		"departement": "Manche",
		"country": "France"
	},
	{
		"city": "Cherbourg - Hôpital Maritime",
		"departement": "Manche",
		"country": "France"
	},
	{
		"city": "Cherbourg - Hôpital Temporaire",
		"departement": "Manche",
		"country": "France"
	},
	{
		"city": "Cherbourg - Hôpital Temporaire Casino - méningite cérébro-spinale",
		"departement": "Manche",
		"country": "France"
	},
	{
		"city": "Cherbourg - Hôpital Temporaire du Lycée",
		"departement": "Manche",
		"country": "France"
	},
	{
		"city": "Cherbourg - Hôpital Temporaire du Lycée de Cher",
		"departement": "Manche",
		"country": "France"
	},
	{
		"city": "Chérigné"
	},
	{
		"city": "Cherveix-Cubas"
	},
	{
		"city": "Chestres",
		"departement": "Ardennes",
		"country": "France"
	},
	{
		"city": "Chevillon - Combat de Chézy",
		"departement": "Aisne",
		"country": "France"
	},
	{
		"city": "Chevincourt",
		"departement": "Oise",
		"country": "France"
	},
	{
		"city": "Chevregny",
		"departement": "Aisne",
		"country": "France"
	},
	{
		"city": "Chevreux",
		"departement": "Aisne",
		"country": "France"
	},
	{
		"city": "Chevrigny",
		"departement": "Aisne",
		"country": "France"
	},
	{
		"city": "Chezy",
		"departement": "Aisne",
		"country": "France"
	},
	{
		"city": "Chézy",
		"departement": "Aisne",
		"country": "France"
	},
	{
		"city": "Chezy-en-Orxois",
		"departement": "Aisne",
		"country": "France"
	},
	{
		"city": "Chigny",
		"departement": "Aisne",
		"country": "France"
	},
	{
		"city": "Chigny les Roses - Ambulance n°1/89",
		"departement": "Marne",
		"country": "France"
	},
	{
		"city": "Chilly",
		"departement": "Somme",
		"country": "France"
	},
	{
		"city": "Chinon",
		"departement": "Indre-et-Loire",
		"country": "France"
	},
	{
		"city": "Chiry",
		"departement": "Somme",
		"country": "France"
	},
	{
		"city": "Choisy-au-Bac",
		"departement": "Oise",
		"country": "France"
	},
	{
		"city": "Choisy-au-Bac (Francport)",
		"departement": "Oise",
		"country": "France"
	},
	{
		"city": "Choisy-le-Roi - Hôpital Auxiliaire",
		"departement": "Seine",
		"country": "France"
	},
	{
		"city": "Cholet"
	},
	{
		"city": "Chuignes",
		"departement": "Somme",
		"country": "France"
	},
	{
		"city": "Chuignolles Près Froissy",
		"departement": "Somme",
		"country": "France"
	},
	{
		"city": "Cierges",
		"departement": "Meuse",
		"country": "France"
	},
	{
		"city": "Clairfage",
		"departement": "Somme",
		"country": "France"
	},
	{
		"city": "Clairvaux - Hôpital Temporaire",
		"departement": "Aube",
		"country": "France"
	},
	{
		"city": "Clamecy",
		"departement": "Aisne",
		"country": "France"
	},
	{
		"city": "Clamecy - Hôpital Complémentaire n°36",
		"departement": "Nièvre",
		"country": "France"
	},
	{
		"city": "Clausen",
		"departement": "Allemagne",
		"country": "Allemagne"
	},
	{
		"city": "Cléré"
	},
	{
		"city": "Clermont - Hôpital Auxiliaire",
		"departement": "Oise",
		"country": "France"
	},
	{
		"city": "Clermont - Hôpital n°15",
		"departement": "Oise",
		"country": "France"
	},
	{
		"city": "Clermont-Ferrand",
		"departement": "Puy-de-Dôme",
		"country": "France"
	},
	{
		"city": "Clermont-Ferrand - Hôpital",
		"departement": "Puy-de-Dôme",
		"country": "France"
	},
	{
		"city": "Clermont-sur-Oise - Asile d'Aliénés",
		"departement": "Oise",
		"country": "France"
	},
	{
		"city": "Cléry",
		"departement": "Somme",
		"country": "France"
	},
	{
		"city": "Cléry sur Somme",
		"departement": "Somme",
		"country": "France"
	},
	{
		"city": "Clis en Guérande",
		"departement": "Loire Inférieure",
		"country": "France"
	},
	{
		"city": "Clisson"
	},
	{
		"city": "Coblence - Lazarett",
		"departement": "Allemagne",
		"country": "Allemagne"
	},
	{
		"city": "Coeuvres",
		"departement": "Aisne",
		"country": "France"
	},
	{
		"city": "Coeuvres - Ambulance n°5/13",
		"departement": "Aisne",
		"country": "France"
	},
	{
		"city": "Cognac",
		"departement": "Charente-Maritime",
		"country": "France"
	},
	{
		"city": "Cognac - Hôpital",
		"departement": "Charente-Maritime",
		"country": "France"
	},
	{
		"city": "Cognac - Hôpital Bénévole n°128 Bis",
		"departement": "Charente-Maritime",
		"country": "France"
	},
	{
		"city": "Cognac - Hôpital n°5",
		"departement": "Charente-Maritime",
		"country": "France"
	},
	{
		"city": "Cognardière",
		"departement": "Loire Inférieure",
		"country": "France"
	},
	{
		"city": "Coincy l'Abbaye",
		"departement": "Aisne",
		"country": "France"
	},
	{
		"city": "Coivrel",
		"departement": "Oise",
		"country": "France"
	},
	{
		"city": "Coizard - Joches",
		"departement": "Marne",
		"country": "France"
	},
	{
		"city": "Coizard Joches",
		"departement": "Marne",
		"country": "France"
	},
	{
		"city": "Colicamps",
		"departement": "Somme",
		"country": "France"
	},
	{
		"city": "Colimcamps",
		"departement": "Somme",
		"country": "France"
	},
	{
		"city": "Colincamp",
		"departement": "Somme",
		"country": "France"
	},
	{
		"city": "Colincamps",
		"departement": "Somme",
		"country": "France"
	},
	{
		"city": "Collège Jette-Saint-Pierre - Ambulance 242",
		"departement": "Belgique",
		"country": "Belgique"
	},
	{
		"city": "Colline d'Achi Baba - Presqu'île de Gallipoli",
		"departement": "Turquie",
		"country": "Turquie"
	},
	{
		"city": "Colmar",
		"departement": "Haut-Rhin",
		"country": "France"
	},
	{
		"city": "Cologne",
		"departement": "Allemagne",
		"country": "Allemagne"
	},
	{
		"city": "Comantre",
		"departement": "Marne",
		"country": "France"
	},
	{
		"city": "Combat d'Ayencourt",
		"departement": "Oise",
		"country": "France"
	},
	{
		"city": "combat de Bois Hault",
		"departement": "Meuse",
		"country": "France"
	},
	{
		"city": "Combat de Carlepont",
		"departement": "Oise",
		"country": "France"
	},
	{
		"city": "Combat de Courjoil",
		"departement": "Aisne",
		"country": "France"
	},
	{
		"city": "Combat de Gratt Viershatt",
		"departement": "Belgique",
		"country": "Belgique"
	},
	{
		"city": "Combat de l'Aisne",
		"departement": "Aisne",
		"country": "France"
	},
	{
		"city": "Combat de la Ferme de la Royère",
		"departement": "Aisne",
		"country": "France"
	},
	{
		"city": "Combat de la Forêt d'Argonne",
		"departement": "Meuse",
		"country": "France"
	},
	{
		"city": "Combat de la Marne - Trelou sur Marne",
		"departement": "Marne",
		"country": "France"
	},
	{
		"city": "Combat de la Noulette",
		"departement": "Pas-de-Calais",
		"country": "France"
	},
	{
		"city": "Combat de la Somme - Route de Péronne",
		"departement": "Somme",
		"country": "France"
	},
	{
		"city": "Combat de Lizerne",
		"departement": "Belgique",
		"country": "Belgique"
	},
	{
		"city": "Combat de Locre",
		"departement": "Belgique",
		"country": "Belgique"
	},
	{
		"city": "Combat de Saint Blaise",
		"departement": "Alsace",
		"country": "France"
	},
	{
		"city": "Combat de Selve - commune de Sissonne",
		"departement": "Aisne",
		"country": "France"
	},
	{
		"city": "Combat de Treloup",
		"departement": "Aisne",
		"country": "France"
	},
	{
		"city": "Combat de Verdun",
		"departement": "Meuse",
		"country": "France"
	},
	{
		"city": "Combat du Bois de Cernay",
		"departement": "Marne",
		"country": "France"
	},
	{
		"city": "Combat du Mont des Tombes - Commune de Leuilly-sous-Coucy",
		"departement": "Aisne",
		"country": "France"
	},
	{
		"city": "Combat du Mont Renaud",
		"departement": "Oise",
		"country": "France"
	},
	{
		"city": "Combat du Signal de Xon",
		"departement": "Meurthe-et-Moselle",
		"country": "France"
	},
	{
		"city": "Combat du Souchez",
		"departement": "Pas-de-Calais",
		"country": "France"
	},
	{
		"city": "Combat du Têton - Commune de Moronvilliers",
		"departement": "Marne",
		"country": "France"
	},
	{
		"city": "Combats au sud de l'Ourcq",
		"departement": "Aisne",
		"country": "France"
	},
	{
		"city": "Combats d'Angres",
		"departement": "Pas-de-Calais",
		"country": "France"
	},
	{
		"city": "Combats de Baconnes",
		"departement": "Marne",
		"country": "France"
	}
]